random_password_creator-0.5.dist-info/licenses/LICENSE
rpc/RandomPasswordCreator.py
rpc/__init__.py
random_password_creator-0.5.dist-info/METADATA
random_password_creator-0.5.dist-info/WHEEL
random_password_creator-0.5.dist-info/entry_points.txt
random_password_creator-0.5.dist-info/top_level.txt
random_password_creator-0.5.dist-info/RECORD
