Metadata-Version: 2.4
Name: random-password-creator
Version: 0.5
Summary: A simple command-line tool to generate random and secure passwords using the Python Standard Library
Author-email: Giovanni Tognini Bonelli Sinclair <sinclair.giovanni@gmail.com>
License: Apache-2.0
Project-URL: Homepage, https://github.com/GTBSinclair/RandomPasswordCreator
Project-URL: Issues, https://github.com/GTBSinclair/RandomPasswordCreator/issues
Keywords: password,cli,security,generator
Requires-Python: >=3.8
License-File: LICENSE
Dynamic: license-file
